{
  "heading": "Our gallery",
  "sliderButtons": {
    "nextBtnLabel": "Back",
    "prevBtnLabel": "Next"
  },
  "galleryItems": [
    {
      "order": 1,
      "name": "mountain",
      "desc": "Beautiful mountainous landscape with hills and clouds"
    },
    {
      "order": 2,
      "name": "lake",
      "desc": "Breathtaking view of a lake surrounded by high Carpathian mountains"
    },
    {
      "order": 3,
      "name": "forest",
      "desc": "Exciting landscape of the Carpathian hills and forest in a bit foggy weather"
    }
  ]
}
